{"cate":"히알루론산"}
{"cate":"cpu"}
{"cate":"성인용기저귀"}
{"cate":"odd"}
{"cate":"가르시니아"}
{"cate":"하이브리드"}
{"cate":"선글라스 케이스"}
{"cate":"커피"}
{"cate":"저주파안마기"}
{"cate":"cla"}
{"cate":"pc케이스"}
{"cate":"가베"}
{"cate":"축구연습용품"}
{"cate":"소품가구"}
{"cate":"마스크시트"}
{"cate":"도장"}
{"cate":"고양이 간식"}
{"cate":"타악기"}
{"cate":"기타모니터주변기기"}
{"cate":"dac"}
{"cate":"dvd"}
{"cate":"전기밥솥"}
{"cate":"쿠션안마기"}
{"cate":"잼"}
{"cate":"아이스박스"}
{"cate":"ssd"}
{"cate":"사무용가구"}
{"cate":"베이스메이크업"}
{"cate":"세정제"}
{"cate":"소형기계"}
{"cate":"mtb"}
{"cate":"요이불세트"}
{"cate":"기내용 캐리어"}
{"cate":"포스터"}
{"cate":"pc"}
{"cate":"pmp"}
{"cate":"수유가리개"}
{"cate":"강아지 장난감"}
{"cate":"장난감정리함"}
{"cate":"솔"}
{"cate":"아이스크림"}
{"cate":"트위스트"}
{"cate":"전자레인지"}
{"cate":"기타축구용품"}
{"cate":"식용식물"}
{"cate":"pmp액세서리"}
{"cate":"장난감소독기"}
{"cate":"스피커"}
{"cate":"gps"}
{"cate":"마스카라"}
{"cate":"전방"}
{"cate":"커튼"}
{"cate":"이불솜"}
{"cate":"그립"}
{"cate":"해바라기씨유"}
{"cate":"테이블"}
{"cate":"n"}
{"cate":"용품"}
{"cate":"배드민턴의류"}
{"cate":"인테리어용품"}
{"cate":"강아지 간식"}
{"cate":"클렌징폼"}
{"cate":"장식미니어처"}
{"cate":"기타야구용품"}
{"cate":"전기포트"}
{"cate":"cd"}
{"cate":"웨어러블 디바이스"}
{"cate":"고양이 사료"}
{"cate":"인라인스케이트"}
{"cate":"식초"}
{"cate":"도복"}
{"cate":"차량실내용품"}
{"cate":"쿠키"}
{"cate":"파워서플라이"}
{"cate":"팬티"}
{"cate":"고양이 장난감"}
{"cate":"목공공구"}
{"cate":"데코스티커"}
{"cate":"키보드키스킨"}
{"cate":"실커튼"}
{"cate":"의자"}
{"cate":"유치보관함"}
{"cate":"내비게이션"}
{"cate":"rc"}
{"cate":"hdd"}
{"cate":"휴대폰이어캡"}
{"cate":"수영"}
{"cate":"커피자판기"}
{"cate":"원예"}
{"cate":"고양이 캣타워"}
{"cate":"복대"}
{"cate":"휴대폰거치대"}
{"cate":"생선"}
{"cate":"tv"}
{"cate":"제모제"}
{"cate":"dvr"}
{"cate":"기저귀휴지통"}
{"cate":"벨트마사지"}
{"cate":"카메라렌즈"}
{"cate":"수예"}
{"cate":"콩"}
{"cate":"공기정화기"}
{"cate":"메이크업베이스"}
{"cate":"장식장"}
{"cate":"봉"}
{"cate":"오디오"}
{"cate":"lp"}
{"cate":"베개솜"}
{"cate":"떡볶이"}
{"cate":"매트커버세트"}
{"cate":"강아지 사료"}
{"cate":"트레이닝복"}
{"cate":"기포"}
{"cate":"기타통조림"}
{"cate":"주얼리세트"}
{"cate":"골프연습용품"}
{"cate":"연유"}
{"cate":"모서리보호대"}
{"cate":"전동휠"}
{"cate":"승마운동기"}
{"cate":"탁구대"}
{"cate":"유아동언더웨어"}
{"cate":"자동차용품"}
{"cate":"클렌징오일"}
{"cate":"에어프라이어"}
{"cate":"카레"}
{"cate":"기타배구용품"}
{"cate":"복근운동기구"}
{"cate":"스프레드"}
{"cate":"유아"}
{"cate":"매직기"}
{"cate":"단화"}
{"cate":"무릎보호대"}
{"cate":"기타"}
{"cate":"침구세트"}
{"cate":"헤어스타일링"}
{"cate":"잔"}
{"cate":"비디오"}
{"cate":"식기세척"}
{"cate":"코코아"}
{"cate":"diy자재"}
{"cate":"양산"}
{"cate":"필름카메라"}
{"cate":"ram"}
{"cate":"매트솜"}
{"cate":"기저귀"}
{"cate":"요구르트제조기"}
{"cate":"설비공구"}
{"cate":"제습"}
{"cate":"검도"}
{"cate":"두부두유제조기"}
{"cate":"넥타이"}
{"cate":"볼링"}
{"cate":"드레스"}
{"cate":"옷걸이"}
{"cate":"제과"}
{"cate":"발각질제거기"}
{"cate":"발목보호대"}
{"cate":"요"}
{"cate":"생수"}
{"cate":"영상플레이어"}
{"cate":"미술놀이"}
{"cate":"강아지 배변용품"}
{"cate":"아동"}
{"cate":"비료"}
{"cate":"토시"}
{"cate":"스킨스쿠버"}
{"cate":"nas"}
{"cate":"임부용수영복"}
{"cate":"모니터주변기기"}
{"cate":"바디슬리밍"}
{"cate":"커프스"}
{"cate":"기타캠핑용품"}
{"cate":"메모리카드"}
{"cate":"요가"}
{"cate":"두유"}
{"cate":"치석제거기"}
{"cate":"간편조리식품"}
{"cate":"기타악기"}
{"cate":"다이어트차"}
{"cate":"블루투스동글"}
{"cate":"면도기"}
{"cate":"헤어스프레이"}
{"cate":"얼룩제거제"}
{"cate":"학습기기"}
{"cate":"트리트먼트"}
